{
    "city": 1,
    "initialStart": [
        18.03363,
        59.31616
    ],
    "trips": [
        {
            "summary": {
                "distance": 848.9,
                "duration": 148.2
            },
            "user": {
                "id": 69,
                "token": "eyJhbGciOiJIUzI1NiIsInR5cCI6IkpXVCJ9.eyJpZCI6NjksInJvbGUiOiJ1c2VyIiwiaWF0IjoxNzAwOTMyMDcxLCJleHAiOjE3MzI0NjgwNzF9.DQ-UD4uRNzZwDcgBcDmcMy2j4EPlcn1X4ICKi3wRY80"
            },
            "coords": [
                [
                    18.03363,
                    59.31616
                ],
                [
                    18.03328,
                    59.31673
                ],
                [
                    18.03323,
                    59.31681
                ],
                [
                    18.03267,
                    59.31783
                ],
                [
                    18.03259,
                    59.31793
                ],
                [
                    18.03264,
                    59.31801
                ],
                [
                    18.03224,
                    59.3188
                ],
                [
                    18.03211,
                    59.31878
                ],
                [
                    18.03197,
                    59.31876
                ],
                [
                    18.03183,
                    59.31874
                ],
                [
                    18.03189,
                    59.31861
                ],
                [
                    18.0319,
                    59.31848
                ],
                [
                    18.03199,
                    59.3183
                ],
                [
                    18.03186,
                    59.31828
                ],
                [
                    18.0317,
                    59.31828
                ],
                [
                    18.03156,
                    59.31829
                ],
                [
                    18.03085,
                    59.31842
                ],
                [
                    18.0306,
                    59.31847
                ],
                [
                    18.03042,
                    59.3185
                ],
                [
                    18.03023,
                    59.3185
                ],
                [
                    18.0286,
                    59.3184
                ],
                [
                    18.0284,
                    59.31839
                ],
                [
                    18.02785,
                    59.31832
                ],
                [
                    18.02726,
                    59.31828
                ],
                [
                    18.02759,
                    59.3173
                ],
                [
                    18.02756,
                    59.31722
                ],
                [
                    18.02823,
                    59.31729
                ],
                [
                    18.02835,
                    59.31698
                ]
            ]
        },
        {
            "summary": {
                "distance": 658.6,
                "duration": 199.9
            },
            "user": {
                "id": 70,
                "token": "eyJhbGciOiJIUzI1NiIsInR5cCI6IkpXVCJ9.eyJpZCI6NzAsInJvbGUiOiJ1c2VyIiwiaWF0IjoxNzAwOTMyMDcxLCJleHAiOjE3MzI0NjgwNzF9.XTxPhd-zRlQqQyhm46nraw5kG2BlU1Ehfz0bAZBMV4g"
            },
            "coords": [
                [
                    18.02835,
                    59.31698
                ],
                [
                    18.02823,
                    59.31729
                ],
                [
                    18.02756,
                    59.31722
                ],
                [
                    18.02759,
                    59.3173
                ],
                [
                    18.02726,
                    59.31828
                ],
                [
                    18.02665,
                    59.3184
                ],
                [
                    18.0265,
                    59.31842
                ],
                [
                    18.02586,
                    59.31854
                ],
                [
                    18.02573,
                    59.31856
                ],
                [
                    18.02554,
                    59.31855
                ],
                [
                    18.02459,
                    59.31833
                ],
                [
                    18.02435,
                    59.31826
                ],
                [
                    18.02388,
                    59.31817
                ],
                [
                    18.02373,
                    59.31814
                ],
                [
                    18.02373,
                    59.31791
                ],
                [
                    18.02353,
                    59.31785
                ],
                [
                    18.02351,
                    59.31749
                ],
                [
                    18.0235,
                    59.31746
                ],
                [
                    18.02343,
                    59.31744
                ],
                [
                    18.02328,
                    59.31744
                ],
                [
                    18.02311,
                    59.31745
                ],
                [
                    18.02294,
                    59.31746
                ],
                [
                    18.02294,
                    59.31741
                ],
                [
                    18.0227,
                    59.31741
                ],
                [
                    18.0227,
                    59.31739
                ],
                [
                    18.02288,
                    59.31739
                ],
                [
                    18.02288,
                    59.31736
                ],
                [
                    18.0227,
                    59.31736
                ],
                [
                    18.02265,
                    59.31734
                ],
                [
                    18.02257,
                    59.31734
                ],
                [
                    18.02257,
                    59.31718
                ],
                [
                    18.02242,
                    59.31718
                ],
                [
                    18.02241,
                    59.31705
                ],
                [
                    18.02241,
                    59.31697
                ],
                [
                    18.02235,
                    59.31693
                ],
                [
                    18.02189,
                    59.31694
                ]
            ]
        }
    ]
}