{
    "city": 2,
    "initialStart": [
        13.57335,
        59.4062
    ],
    "trips": [
        {
            "summary": {
                "distance": "",
                "duration": ""
            },
            "user": {
                "id": 1181,
                "token": "eyJhbGciOiJIUzI1NiIsInR5cCI6IkpXVCJ9.eyJpZCI6MTE4MSwicm9sZSI6InVzZXIiLCJpYXQiOjE3MDA5NDg1OTcsImV4cCI6MTczMjQ4NDU5N30.02TSKG7mk2E64CdAOj8RVEJ-HE7IWZtQgpM5Buxdkn0"
            },
            "coords": [
                [
                    13.57335,
                    59.4062
                ],
                [
                    13.57449,
                    59.40635
                ],
                [
                    13.57587,
                    59.40638
                ],
                [
                    13.57689,
                    59.4063
                ],
                [
                    13.57757,
                    59.40623
                ],
                [
                    13.57761,
                    59.40606
                ],
                [
                    13.57766,
                    59.40593
                ],
                [
                    13.57766,
                    59.40577
                ],
                [
                    13.57764,
                    59.40569
                ],
                [
                    13.57761,
                    59.4056
                ],
                [
                    13.5775,
                    59.40548
                ],
                [
                    13.57736,
                    59.40536
                ],
                [
                    13.57723,
                    59.4053
                ],
                [
                    13.57691,
                    59.40518
                ],
                [
                    13.5767,
                    59.40514
                ],
                [
                    13.57656,
                    59.40492
                ],
                [
                    13.57651,
                    59.40484
                ],
                [
                    13.57648,
                    59.40479
                ],
                [
                    13.57644,
                    59.40474
                ],
                [
                    13.57619,
                    59.4047
                ]
            ]
        },
        {
            "summary": {
                "distance": "",
                "duration": ""
            },
            "user": {
                "id": 1182,
                "token": "eyJhbGciOiJIUzI1NiIsInR5cCI6IkpXVCJ9.eyJpZCI6MTE4Miwicm9sZSI6InVzZXIiLCJpYXQiOjE3MDA5NDg1OTcsImV4cCI6MTczMjQ4NDU5N30.eWDxEAZfkRZuphDd5SkMJtjZffomqjg7UaT5Lr7G5hc"
            },
            "coords": [
                [
                    13.57618,
                    59.4047
                ],
                [
                    13.57619,
                    59.4047
                ],
                [
                    13.57644,
                    59.40474
                ],
                [
                    13.57648,
                    59.40479
                ],
                [
                    13.57651,
                    59.40484
                ],
                [
                    13.57656,
                    59.40492
                ],
                [
                    13.5767,
                    59.40514
                ],
                [
                    13.57691,
                    59.40518
                ],
                [
                    13.57723,
                    59.4053
                ],
                [
                    13.57736,
                    59.40536
                ],
                [
                    13.5775,
                    59.40548
                ],
                [
                    13.57761,
                    59.4056
                ],
                [
                    13.57764,
                    59.40569
                ],
                [
                    13.57766,
                    59.40577
                ],
                [
                    13.57766,
                    59.40593
                ],
                [
                    13.57761,
                    59.40606
                ],
                [
                    13.57757,
                    59.40623
                ],
                [
                    13.57765,
                    59.40641
                ],
                [
                    13.57726,
                    59.40645
                ],
                [
                    13.57616,
                    59.40651
                ]
            ]
        }
    ],
    "apiKey": "89289bd6a0a8e07292c88ae591638a14"
}