{
    "city": 2,
    "initialStart": [
        13.49691,
        59.40296
    ],
    "trips": [
        {
            "summary": {
                "distance": "",
                "duration": ""
            },
            "user": {
                "id": 1207,
                "token": "eyJhbGciOiJIUzI1NiIsInR5cCI6IkpXVCJ9.eyJpZCI6MTIwNywicm9sZSI6InVzZXIiLCJpYXQiOjE3MDA5NDg3MzgsImV4cCI6MTczMjQ4NDczOH0.vPz9NAWEQfFUy2OevBPkRPyhBgMyjMmb20nOw9r9zJk"
            },
            "coords": [
                [
                    13.49691,
                    59.40296
                ],
                [
                    13.49639,
                    59.40293
                ],
                [
                    13.49663,
                    59.40229
                ],
                [
                    13.49747,
                    59.40094
                ],
                [
                    13.49765,
                    59.40074
                ],
                [
                    13.49785,
                    59.40056
                ],
                [
                    13.49839,
                    59.40018
                ],
                [
                    13.49872,
                    59.39998
                ],
                [
                    13.49954,
                    59.39964
                ],
                [
                    13.50166,
                    59.39906
                ],
                [
                    13.50229,
                    59.3989
                ],
                [
                    13.5026,
                    59.39878
                ],
                [
                    13.50285,
                    59.39865
                ],
                [
                    13.50306,
                    59.3985
                ],
                [
                    13.5033,
                    59.39817
                ],
                [
                    13.5035,
                    59.39771
                ],
                [
                    13.50352,
                    59.39746
                ],
                [
                    13.5035,
                    59.39722
                ],
                [
                    13.50352,
                    59.39715
                ],
                [
                    13.50363,
                    59.39713
                ]
            ]
        },
        {
            "summary": {
                "distance": "",
                "duration": ""
            },
            "user": {
                "id": 1208,
                "token": "eyJhbGciOiJIUzI1NiIsInR5cCI6IkpXVCJ9.eyJpZCI6MTIwOCwicm9sZSI6InVzZXIiLCJpYXQiOjE3MDA5NDg3MzgsImV4cCI6MTczMjQ4NDczOH0.ZFhSeak1MT_EU9imI7Z3dLWnt3672aiknv5qeNeTBSs"
            },
            "coords": [
                [
                    13.50363,
                    59.39713
                ],
                [
                    13.50381,
                    59.39714
                ],
                [
                    13.50383,
                    59.39717
                ],
                [
                    13.50383,
                    59.39726
                ],
                [
                    13.50366,
                    59.39739
                ],
                [
                    13.50364,
                    59.39744
                ],
                [
                    13.50357,
                    59.39782
                ],
                [
                    13.50483,
                    59.39791
                ],
                [
                    13.50579,
                    59.39793
                ],
                [
                    13.50612,
                    59.39792
                ],
                [
                    13.50707,
                    59.39787
                ],
                [
                    13.50774,
                    59.3978
                ],
                [
                    13.50845,
                    59.39767
                ],
                [
                    13.5089,
                    59.39757
                ],
                [
                    13.50931,
                    59.39745
                ],
                [
                    13.50941,
                    59.3974
                ],
                [
                    13.50944,
                    59.39734
                ],
                [
                    13.50941,
                    59.39726
                ],
                [
                    13.50923,
                    59.39706
                ],
                [
                    13.50845,
                    59.39731
                ]
            ]
        }
    ]
}