{
    "city": 3,
    "initialStart": [
        12.00579,
        57.68106
    ],
    "trips": [
        {
            "summary": {
                "distance": "",
                "duration": ""
            },
            "user": {
                "id": 1527,
                "token": "eyJhbGciOiJIUzI1NiIsInR5cCI6IkpXVCJ9.eyJpZCI6MTUyNywicm9sZSI6InVzZXIiLCJpYXQiOjE3MDA5NTQ0NTMsImV4cCI6MTczMjQ5MDQ1M30.ZI2GZaPqP_OVRnwSqiCAD4dUaNL1aEhdQj7z1qqY3eY"
            },
            "coords": [
                [
                    12.00579,
                    57.68106
                ],
                [
                    12.00563,
                    57.68127
                ],
                [
                    12.00559,
                    57.6813
                ],
                [
                    12.00543,
                    57.68132
                ],
                [
                    12.00533,
                    57.68131
                ],
                [
                    12.00504,
                    57.68126
                ],
                [
                    12.00477,
                    57.6812
                ],
                [
                    12.00449,
                    57.68115
                ],
                [
                    12.00424,
                    57.6811
                ],
                [
                    12.00405,
                    57.68106
                ],
                [
                    12.00381,
                    57.68101
                ],
                [
                    12.00355,
                    57.68096
                ],
                [
                    12.0035,
                    57.68095
                ],
                [
                    12.00304,
                    57.68085
                ],
                [
                    12.00295,
                    57.68097
                ],
                [
                    12.00228,
                    57.68196
                ],
                [
                    12.00205,
                    57.68231
                ],
                [
                    12.00198,
                    57.68241
                ],
                [
                    12.00144,
                    57.68316
                ],
                [
                    12.0013,
                    57.68337
                ]
            ]
        },
        {
            "summary": {
                "distance": "",
                "duration": ""
            },
            "user": {
                "id": 1528,
                "token": "eyJhbGciOiJIUzI1NiIsInR5cCI6IkpXVCJ9.eyJpZCI6MTUyOCwicm9sZSI6InVzZXIiLCJpYXQiOjE3MDA5NTQ0NTMsImV4cCI6MTczMjQ5MDQ1M30.qLDCIHpSGCaa8i4Zj8C5TohBt39P4vc2hTaQTbxhtxQ"
            },
            "coords": [
                [
                    12.0013,
                    57.68337
                ],
                [
                    12.00126,
                    57.68347
                ],
                [
                    12.0013,
                    57.68361
                ],
                [
                    12.00147,
                    57.68358
                ],
                [
                    12.00165,
                    57.68361
                ],
                [
                    12.00217,
                    57.68374
                ],
                [
                    12.00204,
                    57.68395
                ],
                [
                    12.00196,
                    57.68414
                ],
                [
                    12.0019,
                    57.68422
                ],
                [
                    12.00101,
                    57.68413
                ],
                [
                    12.00091,
                    57.68411
                ],
                [
                    12.00078,
                    57.68403
                ],
                [
                    12.00067,
                    57.68403
                ],
                [
                    12.00045,
                    57.68402
                ],
                [
                    12.00037,
                    57.68406
                ],
                [
                    12.00035,
                    57.68408
                ],
                [
                    11.99991,
                    57.68473
                ],
                [
                    11.99942,
                    57.68539
                ],
                [
                    11.99903,
                    57.68584
                ],
                [
                    11.99862,
                    57.68623
                ]
            ]
        }
    ]
}